{"key":"user_750","kafka_timestamp":"2025-10-08T04:30:32.836Z","timestamp":"2025-10-08T04:30:32.835Z","user_id":"user_750","product_id":"food_snacks_73","quantity":3,"price":427.24,"category":"Food"}
{"key":"user_980","kafka_timestamp":"2025-10-08T04:30:39.797Z","timestamp":"2025-10-08T04:30:39.797Z","user_id":"user_980","product_id":"electronics_tablet_64","quantity":3,"price":252.13,"category":"Electronics"}
{"key":"user_650","kafka_timestamp":"2025-10-08T04:30:52.014Z","timestamp":"2025-10-08T04:30:52.014Z","user_id":"user_650","product_id":"electronics_phone_99","quantity":4,"price":227.53,"category":"Electronics"}
